manabi/__init__.py
manabi/__snapshots__/filesystem_test.ambr
manabi/auth.py
manabi/filesystem.py
manabi/lock.py
manabi/log.py
manabi/mypy_fix.py
manabi/token.py
manabi/type_alias.py
manabi/util.py
manabi_migrations/__init__.py
manabi_migrations/apps.py
manabi_migrations/migrations/0001_initial.py
manabi_migrations/migrations/0002_alter_lock_token.py
manabi_migrations/migrations/__init__.py
manabi_migrations/models.py
manabi-2.0.1.dist-info/LICENSE
manabi-2.0.1.dist-info/METADATA
manabi-2.0.1.dist-info/WHEEL
manabi-2.0.1.dist-info/RECORD
