Metadata-Version: 2.3
Name: manabi
Version: 2.0.1
Summary: Provide WebDAV access for documents.
License: AGPL-3.0-or-later
Author: Adfinis AG
Requires-Python: >=3.12,<4
Classifier: Environment :: Web Environment
Classifier: Intended Audience :: Developers
Classifier: License :: OSI Approved :: GNU Affero General Public License v3 or later (AGPLv3+)
Classifier: License :: OSI Approved :: GNU General Public License v3 or later (GPLv3+)
Classifier: Operating System :: OS Independent
Classifier: Programming Language :: Python :: 3
Classifier: Programming Language :: Python :: 3.12
Classifier: Programming Language :: Python :: 3.13
Classifier: Programming Language :: Python :: 3.10
Classifier: Topic :: Internet :: WWW/HTTP
Classifier: Topic :: Internet :: WWW/HTTP :: Dynamic Content
Requires-Dist: WsgiDAV (>=4.3.0,<5.0.0)
Requires-Dist: attrs (>=23.1,<26.0)
Requires-Dist: boto3 (>=1.34.21,<2.0.0)
Requires-Dist: django (>=4.2,<5.3)
Requires-Dist: psycopg-binary (>=3.2.4,<4.0.0)
Requires-Dist: psycopg[binary] (>=3.2.4,<4.0.0)
Requires-Dist: pybase62 (>=1.0.0,<2.0.0)
Requires-Dist: pybranca (>=0.5.0,<0.6.0)
Requires-Dist: smart-open[s3] (>=6.4,<8.0)
Requires-Dist: u-msgpack-python (>=2.8.0,<3.0.0)
Project-URL: Homepage, https://github.com/projectcaluma/manabi
Project-URL: Repository, https://github.com/projectcaluma/manabi
